webfleet_connect/__init__.py
webfleet_connect/config.py
webfleet_connect/connection.py
webfleet_connect/credentials.py
webfleet_connect/error.py
webfleet_connect/session.py
webfleet_connect/webfleet_connect.py
webfleet_connect/webfleet_connect_error.py
webfleet_connect/webfleet_connect_response.py
webfleet_connect/actions/__init__.py
webfleet_connect/actions/action.py
webfleet_connect/format_handlers/__init__.py
webfleet_connect/format_handlers/csv_error_parser.py
webfleet_connect/format_handlers/csv_response_parser.py
webfleet_connect/format_handlers/json_error_parser.py
webfleet_connect/format_handlers/json_response_parser.py
webfleet_connect/params/__init__.py
webfleet_connect/params/defult_param.py
webfleet_connect/params/param.py
webfleet_connect/params/params_factory.py
webfleet_connect-0.1.29.dist-info/LICENSE
webfleet_connect-0.1.29.dist-info/METADATA
webfleet_connect-0.1.29.dist-info/WHEEL
webfleet_connect-0.1.29.dist-info/top_level.txt
webfleet_connect-0.1.29.dist-info/RECORD
